alertmanager/__init__.py
alertmanager/__version__.py
alertmanager/alert_objects.py
alertmanager/alertmanager.py
pylertalertmanager-0.1.1.dist-info/LICENSE
pylertalertmanager-0.1.1.dist-info/METADATA
pylertalertmanager-0.1.1.dist-info/WHEEL
pylertalertmanager-0.1.1.dist-info/top_level.txt
pylertalertmanager-0.1.1.dist-info/RECORD
