Metadata-Version: 2.1
Name: pylertalertmanager
Version: 0.1.1
Summary: Library to ease interaction with Alert Manager API.
Home-page: https://github.com/ABORGT/PylertAlertManager.git
Author: Tyler Coil
Author-email: kamori.goat@gmail.com
License: MIT
Platform: UNKNOWN
Classifier: License :: OSI Approved :: MIT License
Classifier: Programming Language :: Python :: 3
Classifier: Topic :: System :: Systems Administration
Classifier: Topic :: Software Development :: Libraries
Classifier: Topic :: Software Development :: Libraries :: Python Modules
Requires-Python: >=3.4.0
Requires-Dist: maya (>=0.3.4)
Requires-Dist: python-box (>=3.1.1)
Requires-Dist: requests (>=2.20.0)
